pargen.v
`timescale 1ns/1ns

module pbit(A,cbit,o);
    input [6:0] A;
    input cbit;
    output o;
    assign o=A[0]^A[1]^A[2]^A[3]^A[4]^A[5]^A[6]^cbit;
endmodule

module pbit2(A,cbit,o);
    input [7:0] A;
    input cbit;
    output o;
    assign o=A[0]^A[1]^A[2]^A[3]^A[4]^A[5]^A[6]^A[7]^cbit^1;
endmodule

pargen_tb.v
`timescale 1ns/1ns

module test();
    reg [6:0] A;
    reg cbit;
    wire o;

    pbit dut(.A(A),.cbit(cbit),.o(o));

    initial begin
        A = 0;
        cbit = 0;
        $dumpfile("pargen_tb.vcd");
        $dumpvars(0, test);

        #2560 $finish;
    end

    /* Generation of input patterns to simulate the UUT */
    // a, b and c will got through all possible combinations
    always
        #20 A = A + 1;
    always
        #10 cbit = ~cbit;

endmodule

module test2();
    reg [7:0] A;
    reg cbit;
    wire o;

    pbit2 dut(.A(A),.cbit(cbit),.o(o));

    initial begin
        A = 0;
        cbit = 0;
        $dumpfile("parcheck_tb.vcd");
        $dumpvars(0, test2);

        #5120 $finish;
    end

    /* Generation of input patterns to simulate the UUT */
    // a, b and c will got through all possible combinations
    always
        #20 A = A + 1;
    always
        #10 cbit = ~cbit;

endmodule

pargen_tb.vcd
$date
	Tue Sep 12 18:22:56 2023
$end
$version
	Icarus Verilog
$end
$timescale
	1ns
$end
$scope module test $end
$var wire 1 ! o $end
$var reg 7 " A [6:0] $end
$var reg 1 # cbit $end
$scope module dut $end
$var wire 7 $ A [6:0] $end
$var wire 1 # cbit $end
$var wire 1 ! o $end
$upscope $end
$upscope $end
$scope module test2 $end
$var wire 1 % o $end
$var reg 8 & A [7:0] $end
$var reg 1 ' cbit $end
$scope module dut $end
$var wire 8 ( A [7:0] $end
$var wire 1 ' cbit $end
$var wire 1 % o $end
$upscope $end
$upscope $end
$enddefinitions $end
#0
$dumpvars
b0 (
0'
b0 &
1%
b0 $
0#
b0 "
0!
$end
#10
0%
1!
1'
1#
#20
0%
1!
0'
0#
b1 &
b1 (
b1 "
b1 $
#30
1%
0!
1'
1#
#40
0%
1!
0'
0#
b10 &
b10 (
b10 "
b10 $
#50
1%
0!
1'
1#
#60
1%
0!
0'
0#
b11 &
b11 (
b11 "
b11 $
#70
0%
1!
1'
1#
#80
0%
1!
0'
0#
b100 &
b100 (
b100 "
b100 $
#90
1%
0!
1'
1#
#100
1%
0!
0'
0#
b101 &
b101 (
b101 "
b101 $
#110
0%
1!
1'
1#
#120
1%
0!
0'
0#
b110 &
b110 (
b110 "
b110 $
#130
0%
1!
1'
1#
#140
0%
1!
0'
0#
b111 &
b111 (
b111 "
b111 $
#150
1%
0!
1'
1#
#160
0%
1!
0'
0#
b1000 &
b1000 (
b1000 "
b1000 $
#170
1%
0!
1'
1#
#180
1%
0!
0'
0#
b1001 &
b1001 (
b1001 "
b1001 $
#190
0%
1!
1'
1#
#200
1%
0!
0'
0#
b1010 &
b1010 (
b1010 "
b1010 $
#210
0%
1!
1'
1#
#220
0%
1!
0'
0#
b1011 &
b1011 (
b1011 "
b1011 $
#230
1%
0!
1'
1#
#240
1%
0!
0'
0#
b1100 &
b1100 (
b1100 "
b1100 $
#250
0%
1!
1'
1#
#260
0%
1!
0'
0#
b1101 &
b1101 (
b1101 "
b1101 $
#270
1%
0!
1'
1#
#280
0%
1!
0'
0#
b1110 &
b1110 (
b1110 "
b1110 $
#290
1%
0!
1'
1#
#300
1%
0!
0'
0#
b1111 &
b1111 (
b1111 "
b1111 $
#310
0%
1!
1'
1#
#320
0%
1!
0'
0#
b10000 &
b10000 (
b10000 "
b10000 $
#330
1%
0!
1'
1#
#340
1%
0!
0'
0#
b10001 &
b10001 (
b10001 "
b10001 $
#350
0%
1!
1'
1#
#360
1%
0!
0'
0#
b10010 &
b10010 (
b10010 "
b10010 $
#370
0%
1!
1'
1#
#380
0%
1!
0'
0#
b10011 &
b10011 (
b10011 "
b10011 $
#390
1%
0!
1'
1#
#400
1%
0!
0'
0#
b10100 &
b10100 (
b10100 "
b10100 $
#410
0%
1!
1'
1#
#420
0%
1!
0'
0#
b10101 &
b10101 (
b10101 "
b10101 $
#430
1%
0!
1'
1#
#440
0%
1!
0'
0#
b10110 &
b10110 (
b10110 "
b10110 $
#450
1%
0!
1'
1#
#460
1%
0!
0'
0#
b10111 &
b10111 (
b10111 "
b10111 $
#470
0%
1!
1'
1#
#480
1%
0!
0'
0#
b11000 &
b11000 (
b11000 "
b11000 $
#490
0%
1!
1'
1#
#500
0%
1!
0'
0#
b11001 &
b11001 (
b11001 "
b11001 $
#510
1%
0!
1'
1#
#520
0%
1!
0'
0#
b11010 &
b11010 (
b11010 "
b11010 $
#530
1%
0!
1'
1#
#540
1%
0!
0'
0#
b11011 &
b11011 (
b11011 "
b11011 $
#550
0%
1!
1'
1#
#560
0%
1!
0'
0#
b11100 &
b11100 (
b11100 "
b11100 $
#570
1%
0!
1'
1#
#580
1%
0!
0'
0#
b11101 &
b11101 (
b11101 "
b11101 $
#590
0%
1!
1'
1#
#600
1%
0!
0'
0#
b11110 &
b11110 (
b11110 "
b11110 $
#610
0%
1!
1'
1#
#620
0%
1!
0'
0#
b11111 &
b11111 (
b11111 "
b11111 $
#630
1%
0!
1'
1#
#640
0%
1!
0'
0#
b100000 &
b100000 (
b100000 "
b100000 $
#650
1%
0!
1'
1#
#660
1%
0!
0'
0#
b100001 &
b100001 (
b100001 "
b100001 $
#670
0%
1!
1'
1#
#680
1%
0!
0'
0#
b100010 &
b100010 (
b100010 "
b100010 $
#690
0%
1!
1'
1#
#700
0%
1!
0'
0#
b100011 &
b100011 (
b100011 "
b100011 $
#710
1%
0!
1'
1#
#720
1%
0!
0'
0#
b100100 &
b100100 (
b100100 "
b100100 $
#730
0%
1!
1'
1#
#740
0%
1!
0'
0#
b100101 &
b100101 (
b100101 "
b100101 $
#750
1%
0!
1'
1#
#760
0%
1!
0'
0#
b100110 &
b100110 (
b100110 "
b100110 $
#770
1%
0!
1'
1#
#780
1%
0!
0'
0#
b100111 &
b100111 (
b100111 "
b100111 $
#790
0%
1!
1'
1#
#800
1%
0!
0'
0#
b101000 &
b101000 (
b101000 "
b101000 $
#810
0%
1!
1'
1#
#820
0%
1!
0'
0#
b101001 &
b101001 (
b101001 "
b101001 $
#830
1%
0!
1'
1#
#840
0%
1!
0'
0#
b101010 &
b101010 (
b101010 "
b101010 $
#850
1%
0!
1'
1#
#860
1%
0!
0'
0#
b101011 &
b101011 (
b101011 "
b101011 $
#870
0%
1!
1'
1#
#880
0%
1!
0'
0#
b101100 &
b101100 (
b101100 "
b101100 $
#890
1%
0!
1'
1#
#900
1%
0!
0'
0#
b101101 &
b101101 (
b101101 "
b101101 $
#910
0%
1!
1'
1#
#920
1%
0!
0'
0#
b101110 &
b101110 (
b101110 "
b101110 $
#930
0%
1!
1'
1#
#940
0%
1!
0'
0#
b101111 &
b101111 (
b101111 "
b101111 $
#950
1%
0!
1'
1#
#960
1%
0!
0'
0#
b110000 &
b110000 (
b110000 "
b110000 $
#970
0%
1!
1'
1#
#980
0%
1!
0'
0#
b110001 &
b110001 (
b110001 "
b110001 $
#990
1%
0!
1'
1#
#1000
0%
1!
0'
0#
b110010 &
b110010 (
b110010 "
b110010 $
#1010
1%
0!
1'
1#
#1020
1%
0!
0'
0#
b110011 &
b110011 (
b110011 "
b110011 $
#1030
0%
1!
1'
1#
#1040
0%
1!
0'
0#
b110100 &
b110100 (
b110100 "
b110100 $
#1050
1%
0!
1'
1#
#1060
1%
0!
0'
0#
b110101 &
b110101 (
b110101 "
b110101 $
#1070
0%
1!
1'
1#
#1080
1%
0!
0'
0#
b110110 &
b110110 (
b110110 "
b110110 $
#1090
0%
1!
1'
1#
#1100
0%
1!
0'
0#
b110111 &
b110111 (
b110111 "
b110111 $
#1110
1%
0!
1'
1#
#1120
0%
1!
0'
0#
b111000 &
b111000 (
b111000 "
b111000 $
#1130
1%
0!
1'
1#
#1140
1%
0!
0'
0#
b111001 &
b111001 (
b111001 "
b111001 $
#1150
0%
1!
1'
1#
#1160
1%
0!
0'
0#
b111010 &
b111010 (
b111010 "
b111010 $
#1170
0%
1!
1'
1#
#1180
0%
1!
0'
0#
b111011 &
b111011 (
b111011 "
b111011 $
#1190
1%
0!
1'
1#
#1200
1%
0!
0'
0#
b111100 &
b111100 (
b111100 "
b111100 $
#1210
0%
1!
1'
1#
#1220
0%
1!
0'
0#
b111101 &
b111101 (
b111101 "
b111101 $
#1230
1%
0!
1'
1#
#1240
0%
1!
0'
0#
b111110 &
b111110 (
b111110 "
b111110 $
#1250
1%
0!
1'
1#
#1260
1%
0!
0'
0#
b111111 &
b111111 (
b111111 "
b111111 $
#1270
0%
1!
1'
1#
#1280
0%
1!
0'
0#
b1000000 &
b1000000 (
b1000000 "
b1000000 $
#1290
1%
0!
1'
1#
#1300
1%
0!
0'
0#
b1000001 &
b1000001 (
b1000001 "
b1000001 $
#1310
0%
1!
1'
1#
#1320
1%
0!
0'
0#
b1000010 &
b1000010 (
b1000010 "
b1000010 $
#1330
0%
1!
1'
1#
#1340
0%
1!
0'
0#
b1000011 &
b1000011 (
b1000011 "
b1000011 $
#1350
1%
0!
1'
1#
#1360
1%
0!
0'
0#
b1000100 &
b1000100 (
b1000100 "
b1000100 $
#1370
0%
1!
1'
1#
#1380
0%
1!
0'
0#
b1000101 &
b1000101 (
b1000101 "
b1000101 $
#1390
1%
0!
1'
1#
#1400
0%
1!
0'
0#
b1000110 &
b1000110 (
b1000110 "
b1000110 $
#1410
1%
0!
1'
1#
#1420
1%
0!
0'
0#
b1000111 &
b1000111 (
b1000111 "
b1000111 $
#1430
0%
1!
1'
1#
#1440
1%
0!
0'
0#
b1001000 &
b1001000 (
b1001000 "
b1001000 $
#1450
0%
1!
1'
1#
#1460
0%
1!
0'
0#
b1001001 &
b1001001 (
b1001001 "
b1001001 $
#1470
1%
0!
1'
1#
#1480
0%
1!
0'
0#
b1001010 &
b1001010 (
b1001010 "
b1001010 $
#1490
1%
0!
1'
1#
#1500
1%
0!
0'
0#
b1001011 &
b1001011 (
b1001011 "
b1001011 $
#1510
0%
1!
1'
1#
#1520
0%
1!
0'
0#
b1001100 &
b1001100 (
b1001100 "
b1001100 $
#1530
1%
0!
1'
1#
#1540
1%
0!
0'
0#
b1001101 &
b1001101 (
b1001101 "
b1001101 $
#1550
0%
1!
1'
1#
#1560
1%
0!
0'
0#
b1001110 &
b1001110 (
b1001110 "
b1001110 $
#1570
0%
1!
1'
1#
#1580
0%
1!
0'
0#
b1001111 &
b1001111 (
b1001111 "
b1001111 $
#1590
1%
0!
1'
1#
#1600
1%
0!
0'
0#
b1010000 &
b1010000 (
b1010000 "
b1010000 $
#1610
0%
1!
1'
1#
#1620
0%
1!
0'
0#
b1010001 &
b1010001 (
b1010001 "
b1010001 $
#1630
1%
0!
1'
1#
#1640
0%
1!
0'
0#
b1010010 &
b1010010 (
b1010010 "
b1010010 $
#1650
1%
0!
1'
1#
#1660
1%
0!
0'
0#
b1010011 &
b1010011 (
b1010011 "
b1010011 $
#1670
0%
1!
1'
1#
#1680
0%
1!
0'
0#
b1010100 &
b1010100 (
b1010100 "
b1010100 $
#1690
1%
0!
1'
1#
#1700
1%
0!
0'
0#
b1010101 &
b1010101 (
b1010101 "
b1010101 $
#1710
0%
1!
1'
1#
#1720
1%
0!
0'
0#
b1010110 &
b1010110 (
b1010110 "
b1010110 $
#1730
0%
1!
1'
1#
#1740
0%
1!
0'
0#
b1010111 &
b1010111 (
b1010111 "
b1010111 $
#1750
1%
0!
1'
1#
#1760
0%
1!
0'
0#
b1011000 &
b1011000 (
b1011000 "
b1011000 $
#1770
1%
0!
1'
1#
#1780
1%
0!
0'
0#
b1011001 &
b1011001 (
b1011001 "
b1011001 $
#1790
0%
1!
1'
1#
#1800
1%
0!
0'
0#
b1011010 &
b1011010 (
b1011010 "
b1011010 $
#1810
0%
1!
1'
1#
#1820
0%
1!
0'
0#
b1011011 &
b1011011 (
b1011011 "
b1011011 $
#1830
1%
0!
1'
1#
#1840
1%
0!
0'
0#
b1011100 &
b1011100 (
b1011100 "
b1011100 $
#1850
0%
1!
1'
1#
#1860
0%
1!
0'
0#
b1011101 &
b1011101 (
b1011101 "
b1011101 $
#1870
1%
0!
1'
1#
#1880
0%
1!
0'
0#
b1011110 &
b1011110 (
b1011110 "
b1011110 $
#1890
1%
0!
1'
1#
#1900
1%
0!
0'
0#
b1011111 &
b1011111 (
b1011111 "
b1011111 $
#1910
0%
1!
1'
1#
#1920
1%
0!
0'
0#
b1100000 &
b1100000 (
b1100000 "
b1100000 $
#1930
0%
1!
1'
1#
#1940
0%
1!
0'
0#
b1100001 &
b1100001 (
b1100001 "
b1100001 $
#1950
1%
0!
1'
1#
#1960
0%
1!
0'
0#
b1100010 &
b1100010 (
b1100010 "
b1100010 $
#1970
1%
0!
1'
1#
#1980
1%
0!
0'
0#
b1100011 &
b1100011 (
b1100011 "
b1100011 $
#1990
0%
1!
1'
1#
#2000
0%
1!
0'
0#
b1100100 &
b1100100 (
b1100100 "
b1100100 $
#2010
1%
0!
1'
1#
#2020
1%
0!
0'
0#
b1100101 &
b1100101 (
b1100101 "
b1100101 $
#2030
0%
1!
1'
1#
#2040
1%
0!
0'
0#
b1100110 &
b1100110 (
b1100110 "
b1100110 $
#2050
0%
1!
1'
1#
#2060
0%
1!
0'
0#
b1100111 &
b1100111 (
b1100111 "
b1100111 $
#2070
1%
0!
1'
1#
#2080
0%
1!
0'
0#
b1101000 &
b1101000 (
b1101000 "
b1101000 $
#2090
1%
0!
1'
1#
#2100
1%
0!
0'
0#
b1101001 &
b1101001 (
b1101001 "
b1101001 $
#2110
0%
1!
1'
1#
#2120
1%
0!
0'
0#
b1101010 &
b1101010 (
b1101010 "
b1101010 $
#2130
0%
1!
1'
1#
#2140
0%
1!
0'
0#
b1101011 &
b1101011 (
b1101011 "
b1101011 $
#2150
1%
0!
1'
1#
#2160
1%
0!
0'
0#
b1101100 &
b1101100 (
b1101100 "
b1101100 $
#2170
0%
1!
1'
1#
#2180
0%
1!
0'
0#
b1101101 &
b1101101 (
b1101101 "
b1101101 $
#2190
1%
0!
1'
1#
#2200
0%
1!
0'
0#
b1101110 &
b1101110 (
b1101110 "
b1101110 $
#2210
1%
0!
1'
1#
#2220
1%
0!
0'
0#
b1101111 &
b1101111 (
b1101111 "
b1101111 $
#2230
0%
1!
1'
1#
#2240
0%
1!
0'
0#
b1110000 &
b1110000 (
b1110000 "
b1110000 $
#2250
1%
0!
1'
1#
#2260
1%
0!
0'
0#
b1110001 &
b1110001 (
b1110001 "
b1110001 $
#2270
0%
1!
1'
1#
#2280
1%
0!
0'
0#
b1110010 &
b1110010 (
b1110010 "
b1110010 $
#2290
0%
1!
1'
1#
#2300
0%
1!
0'
0#
b1110011 &
b1110011 (
b1110011 "
b1110011 $
#2310
1%
0!
1'
1#
#2320
1%
0!
0'
0#
b1110100 &
b1110100 (
b1110100 "
b1110100 $
#2330
0%
1!
1'
1#
#2340
0%
1!
0'
0#
b1110101 &
b1110101 (
b1110101 "
b1110101 $
#2350
1%
0!
1'
1#
#2360
0%
1!
0'
0#
b1110110 &
b1110110 (
b1110110 "
b1110110 $
#2370
1%
0!
1'
1#
#2380
1%
0!
0'
0#
b1110111 &
b1110111 (
b1110111 "
b1110111 $
#2390
0%
1!
1'
1#
#2400
1%
0!
0'
0#
b1111000 &
b1111000 (
b1111000 "
b1111000 $
#2410
0%
1!
1'
1#
#2420
0%
1!
0'
0#
b1111001 &
b1111001 (
b1111001 "
b1111001 $
#2430
1%
0!
1'
1#
#2440
0%
1!
0'
0#
b1111010 &
b1111010 (
b1111010 "
b1111010 $
#2450
1%
0!
1'
1#
#2460
1%
0!
0'
0#
b1111011 &
b1111011 (
b1111011 "
b1111011 $
#2470
0%
1!
1'
1#
#2480
0%
1!
0'
0#
b1111100 &
b1111100 (
b1111100 "
b1111100 $
#2490
1%
0!
1'
1#
#2500
1%
0!
0'
0#
b1111101 &
b1111101 (
b1111101 "
b1111101 $
#2510
0%
1!
1'
1#
#2520
1%
0!
0'
0#
b1111110 &
b1111110 (
b1111110 "
b1111110 $
#2530
0%
1!
1'
1#
#2540
0%
1!
0'
0#
b1111111 &
b1111111 (
b1111111 "
b1111111 $
#2550
1%
0!
1'
1#
#2560
0%
0!
0'
0#
b10000000 &
b10000000 (
b0 "
b0 $
